bagdaddy/__init__.py
bagdaddy-0.0.1.dist-info/METADATA
bagdaddy-0.0.1.dist-info/WHEEL
bagdaddy-0.0.1.dist-info/top_level.txt
bagdaddy-0.0.1.dist-info/RECORD
