Metadata-Version: 2.4
Name: bagdaddy
Version: 0.0.1
Summary: An application for DCF analysis of publicly traded companies
Author: Warren Elrod
License: MIT
Classifier: Programming Language :: Python :: 3
Classifier: License :: OSI Approved :: MIT License
Classifier: Operating System :: OS Independent
Requires-Python: >=3.10
